LICENSE
miom/__init__.py
miom/__main__.py
miom/mio.py
miom/miom.py
miom/tools.py
miom-0.9.0b9.dist-info/LICENSE
miom-0.9.0b9.dist-info/WHEEL
miom-0.9.0b9.dist-info/METADATA
miom-0.9.0b9.dist-info/RECORD
