Metadata-Version: 2.1
Name: miom
Version: 0.9.0b9
Summary: Mixed Integer Optimization for Metabolism
Home-page: https://github.com/MetExplore/miom/
License: GPLv3
Keywords: optimization,LP,MIP,metabolism,metabolic-networks
Author: Pablo R. Mier
Author-email: pablo.rodriguez.mier@gmail.com
Requires-Python: >=3.6.1,<4.0.0
Classifier: License :: Other/Proprietary License
Classifier: Programming Language :: Python :: 3
Classifier: Programming Language :: Python :: 3.7
Classifier: Programming Language :: Python :: 3.8
Classifier: Programming Language :: Python :: 3.9
Provides-Extra: all
Provides-Extra: full
Provides-Extra: glpk
Provides-Extra: gurobi
Provides-Extra: mosek
Requires-Dist: Mosek (>=9.3.3,<10.0.0); extra == "mosek" or extra == "all" or extra == "full"
Requires-Dist: PICOS (>=2.2.52,<3.0.0); extra == "glpk" or extra == "gurobi" or extra == "mosek" or extra == "all" or extra == "full"
Requires-Dist: cobra (>=0.22.0,<0.23.0); extra == "full"
Requires-Dist: gurobipy (>=9.1.2,<10.0.0); extra == "gurobi" or extra == "all" or extra == "full"
Requires-Dist: mip (>=1.13.0,<2.0.0)
Requires-Dist: numpy (>=1.19.0,<2.0.0)
Requires-Dist: swiglpk (>=5.0.3,<6.0.0); extra == "glpk" or extra == "all" or extra == "full"
Project-URL: Repository, https://github.com/MetExplore/miom/
